{"batchcomplete": "", "query": {"pages": {"170675472": {"pageid": 170675472, "ns": 6, "title": "File:FIA F1 Imola 2025 No. 27 H\u00fclkenberg.jpg", "index": 1, "imagerepository": "local", "imageinfo": [{"size": 4195337, "width": 4440, "height": 3070, "thumburl": "https://upload.wikimedia.org/wikipedia/commons/thumb/4/41/FIA_F1_Imola_2025_No._27_H%C3%BClkenberg.jpg/1920px-FIA_F1_Imola_2025_No._27_H%C3%BClkenberg.jpg", "thumbwidth": 1920, "thumbheight": 1328, "responsiveUrls": {"2": "https://upload.wikimedia.org/wikipedia/commons/thumb/4/41/FIA_F1_Imola_2025_No._27_H%C3%BClkenberg.jpg/3840px-FIA_F1_Imola_2025_No._27_H%C3%BClkenberg.jpg"}, "url": "https://upload.wikimedia.org/wikipedia/commons/4/41/FIA_F1_Imola_2025_No._27_H%C3%BClkenberg.jpg", "descriptionurl": "https://commons.wikimedia.org/wiki/File:FIA_F1_Imola_2025_No._27_H%C3%BClkenberg.jpg", "descriptionshorturl": "https://commons.wikimedia.org/w/index.php?curid=170675472", "extmetadata": {"DateTime": {"value": "2025-07-25 07:53:57", "source": "mediawiki-metadata", "hidden": ""}, "ObjectName": {"value": "FIA F1 Imola 2025 No. 27 H\u00fclkenberg", "source": "mediawiki-metadata"}, "CommonsMetadataExtension": {"value": 1.2, "source": "extension", "hidden": ""}, "Categories": {"value": "Flickr images reviewed by FlickreviewR 2|Sauber C45 of Nico H\u00fclkenberg|2025 Emilia Romagna Grand Prix", "source": "commons-categories", "hidden": ""}, "Assessments": {"value": "", "source": "commons-categories", "hidden": ""}, "ImageDescription": {"value": "FIA F1 Imola 2025 No. 27 H\u00fclkenberg", "source": "commons-desc-page"}, "DateTimeOriginal": {"value": "2025-05-16 12:01:33", "source": "commons-desc-page"}, "Credit": {"value": "<a rel=\"nofollow\" class=\"external free\" href=\"https://www.flickr.com/photos/69527563@N05/54645989918/\">https://www.flickr.com/photos/69527563@N05/54645989918/</a>", "source": "commons-desc-page"}, "Artist": {"value": "Jen_ross83", "source": "commons-desc-page"}, "LicenseShortName": {"value": "CC BY 4.0", "source": "commons-desc-page", "hidden": ""}, "UsageTerms": {"value": "Creative Commons Attribution 4.0", "source": "commons-desc-page"}, "AttributionRequired": {"value": "true", "source": "commons-desc-page", "hidden": ""}, "LicenseUrl": {"value": "https://creativecommons.org/licenses/by/4.0", "source": "commons-desc-page"}, "Copyrighted": {"value": "True", "source": "commons-desc-page", "hidden": ""}, "Restrictions": {"value": "", "source": "commons-desc-page", "hidden": ""}, "License": {"value": "cc-by-4.0", "source": "commons-templates", "hidden": ""}}}]}}}}