[{"date": "2025-09-21T11:49:58.574000+00:00", "session_key": 9904, "driver_number": 1, "x": 1409, "meeting_key": 1269, "z": -244, "y": -449}, {"date": "2025-09-21T11:49:58.894000+00:00", "session_key": 9904, "driver_number": 1, "x": 1556, "meeting_key": 1269, "z": -244, "y": -387}, {"date": "2025-09-21T11:49:59.074000+00:00", "session_key": 9904, "driver_number": 1, "x": 1702, "meeting_key": 1269, "z": -244, "y": -326}, {"date": "2025-09-21T11:49:59.433000+00:00", "session_key": 9904, "driver_number": 1, "x": 1993, "meeting_key": 1269, "z": -243, "y": -203}, {"date": "2025-09-21T11:49:59.653000+00:00", "session_key": 9904, "driver_number": 1, "x": 2203, "meeting_key": 1269, "z": -243, "y": -115}, {"date": "2025-09-21T11:50:00.013000+00:00", "session_key": 9904, "driver_number": 1, "x": 2459, "meeting_key": 1269, "z": -243, "y": -9}, {"date": "2025-09-21T11:50:00.173000+00:00", "session_key": 9904, "driver_number": 1, "x": 2584, "meeting_key": 1269, "z": -244, "y": 43}, {"date": "2025-09-21T11:50:00.313000+00:00", "session_key": 9904, "driver_number": 1, "x": 2689, "meeting_key": 1269, "z": -244, "y": 88}, {"date": "2025-09-21T11:50:00.513000+00:00", "session_key": 9904, "driver_number": 1, "x": 2828, "meeting_key": 1269, "z": -245, "y": 150}, {"date": "2025-09-21T11:50:00.853000+00:00", "session_key": 9904, "driver_number": 1, "x": 3036, "meeting_key": 1269, "z": -245, "y": 237}, {"date": "2025-09-21T11:50:01.013000+00:00", "session_key": 9904, "driver_number": 1, "x": 3124, "meeting_key": 1269, "z": -245, "y": 269}, {"date": "2025-09-21T11:50:01.293000+00:00", "session_key": 9904, "driver_number": 1, "x": 3266, "meeting_key": 1269, "z": -246, "y": 318}, {"date": "2025-09-21T11:50:01.373000+00:00", "session_key": 9904, "driver_number": 1, "x": 3303, "meeting_key": 1269, "z": -246, "y": 331}, {"date": "2025-09-21T11:50:01.533000+00:00", "session_key": 9904, "driver_number": 1, "x": 3373, "meeting_key": 1269, "z": -247, "y": 358}, {"date": "2025-09-21T11:50:01.853000+00:00", "session_key": 9904, "driver_number": 1, "x": 3488, "meeting_key": 1269, "z": -247, "y": 416}, {"date": "2025-09-21T11:50:02.134000+00:00", "session_key": 9904, "driver_number": 1, "x": 3569, "meeting_key": 1269, "z": -246, "y": 473}, {"date": "2025-09-21T11:50:02.294000+00:00", "session_key": 9904, "driver_number": 1, "x": 3607, "meeting_key": 1269, "z": -247, "y": 510}, {"date": "2025-09-21T11:50:02.494000+00:00", "session_key": 9904, "driver_number": 1, "x": 3650, "meeting_key": 1269, "z": -244, "y": 561}, {"date": "2025-09-21T11:50:02.674000+00:00", "session_key": 9904, "driver_number": 1, "x": 3697, "meeting_key": 1269, "z": -245, "y": 645}, {"date": "2025-09-21T11:50:03.134000+00:00", "session_key": 9904, "driver_number": 1, "x": 3723, "meeting_key": 1269, "z": -245, "y": 750}, {"date": "2025-09-21T11:50:03.214000+00:00", "session_key": 9904, "driver_number": 1, "x": 3725, "meeting_key": 1269, "z": -245, "y": 776}, {"date": "2025-09-21T11:50:03.454000+00:00", "session_key": 9904, "driver_number": 1, "x": 3719, "meeting_key": 1269, "z": -244, "y": 856}, {"date": "2025-09-21T11:50:03.714000+00:00", "session_key": 9904, "driver_number": 1, "x": 3682, "meeting_key": 1269, "z": -244, "y": 991}, {"date": "2025-09-21T11:50:04.074000+00:00", "session_key": 9904, "driver_number": 1, "x": 3646, "meeting_key": 1269, "z": -244, "y": 1081}, {"date": "2025-09-21T11:50:04.254000+00:00", "session_key": 9904, "driver_number": 1, "x": 3614, "meeting_key": 1269, "z": -243, "y": 1151}, {"date": "2025-09-21T11:50:04.514000+00:00", "session_key": 9904, "driver_number": 1, "x": 3541, "meeting_key": 1269, "z": -242, "y": 1310}, {"date": "2025-09-21T11:50:04.914000+00:00", "session_key": 9904, "driver_number": 1, "x": 3487, "meeting_key": 1269, "z": -242, "y": 1436}, {"date": "2025-09-21T11:50:05.194000+00:00", "session_key": 9904, "driver_number": 1, "x": 3431, "meeting_key": 1269, "z": -241, "y": 1572}, {"date": "2025-09-21T11:50:05.314000+00:00", "session_key": 9904, "driver_number": 1, "x": 3406, "meeting_key": 1269, "z": -241, "y": 1633}, {"date": "2025-09-21T11:50:05.534000+00:00", "session_key": 9904, "driver_number": 1, "x": 3358, "meeting_key": 1269, "z": -241, "y": 1746}, {"date": "2025-09-21T11:50:05.834000+00:00", "session_key": 9904, "driver_number": 1, "x": 3287, "meeting_key": 1269, "z": -240, "y": 1905}, {"date": "2025-09-21T11:50:05.933000+00:00", "session_key": 9904, "driver_number": 1, "x": 3263, "meeting_key": 1269, "z": -240, "y": 1959}, {"date": "2025-09-21T11:50:06.153000+00:00", "session_key": 9904, "driver_number": 1, "x": 3207, "meeting_key": 1269, "z": -239, "y": 2081}, {"date": "2025-09-21T11:50:06.393000+00:00", "session_key": 9904, "driver_number": 1, "x": 3115, "meeting_key": 1269, "z": -239, "y": 2286}, {"date": "2025-09-21T11:50:06.893000+00:00", "session_key": 9904, "driver_number": 1, "x": 2979, "meeting_key": 1269, "z": -238, "y": 2594}, {"date": "2025-09-21T11:50:07.313000+00:00", "session_key": 9904, "driver_number": 1, "x": 2878, "meeting_key": 1269, "z": -237, "y": 2822}, {"date": "2025-09-21T11:50:07.453000+00:00", "session_key": 9904, "driver_number": 1, "x": 2836, "meeting_key": 1269, "z": -236, "y": 2916}, {"date": "2025-09-21T11:50:07.713000+00:00", "session_key": 9904, "driver_number": 1, "x": 2768, "meeting_key": 1269, "z": -235, "y": 3070}, {"date": "2025-09-21T11:50:07.893000+00:00", "session_key": 9904, "driver_number": 1, "x": 2725, "meeting_key": 1269, "z": -235, "y": 3167}, {"date": "2025-09-21T11:50:08.894000+00:00", "session_key": 9904, "driver_number": 1, "x": 2514, "meeting_key": 1269, "z": -232, "y": 3608}, {"date": "2025-09-21T11:50:09.254000+00:00", "session_key": 9904, "driver_number": 1, "x": 2468, "meeting_key": 1269, "z": -231, "y": 3655}, {"date": "2025-09-21T11:50:09.574000+00:00", "session_key": 9904, "driver_number": 1, "x": 2341, "meeting_key": 1269, "z": -233, "y": 3692}, {"date": "2025-09-21T11:50:09.854000+00:00", "session_key": 9904, "driver_number": 1, "x": 2299, "meeting_key": 1269, "z": -233, "y": 3688}, {"date": "2025-09-21T11:50:10.114000+00:00", "session_key": 9904, "driver_number": 1, "x": 2225, "meeting_key": 1269, "z": -231, "y": 3671}, {"date": "2025-09-21T11:50:10.314000+00:00", "session_key": 9904, "driver_number": 1, "x": 2169, "meeting_key": 1269, "z": -230, "y": 3655}, {"date": "2025-09-21T11:50:10.594000+00:00", "session_key": 9904, "driver_number": 1, "x": 2090, "meeting_key": 1269, "z": -230, "y": 3629}, {"date": "2025-09-21T11:50:10.754000+00:00", "session_key": 9904, "driver_number": 1, "x": 2045, "meeting_key": 1269, "z": -230, "y": 3612}, {"date": "2025-09-21T11:50:10.994000+00:00", "session_key": 9904, "driver_number": 1, "x": 1972, "meeting_key": 1269, "z": -231, "y": 3584}, {"date": "2025-09-21T11:50:11.274000+00:00", "session_key": 9904, "driver_number": 1, "x": 1880, "meeting_key": 1269, "z": -231, "y": 3547}, {"date": "2025-09-21T11:50:11.294000+00:00", "session_key": 9904, "driver_number": 1, "x": 1873, "meeting_key": 1269, "z": -231, "y": 3544}, {"date": "2025-09-21T11:50:11.674000+00:00", "session_key": 9904, "driver_number": 1, "x": 1710, "meeting_key": 1269, "z": -231, "y": 3481}, {"date": "2025-09-21T11:50:11.934000+00:00", "session_key": 9904, "driver_number": 1, "x": 1634, "meeting_key": 1269, "z": -231, "y": 3453}, {"date": "2025-09-21T11:50:12.294000+00:00", "session_key": 9904, "driver_number": 1, "x": 1469, "meeting_key": 1269, "z": -230, "y": 3393}, {"date": "2025-09-21T11:50:12.434000+00:00", "session_key": 9904, "driver_number": 1, "x": 1401, "meeting_key": 1269, "z": -230, "y": 3368}, {"date": "2025-09-21T11:50:12.613000+00:00", "session_key": 9904, "driver_number": 1, "x": 1313, "meeting_key": 1269, "z": -230, "y": 3335}, {"date": "2025-09-21T11:50:12.853000+00:00", "session_key": 9904, "driver_number": 1, "x": 1190, "meeting_key": 1269, "z": -229, "y": 3290}, {"date": "2025-09-21T11:50:13.053000+00:00", "session_key": 9904, "driver_number": 1, "x": 1029, "meeting_key": 1269, "z": -229, "y": 3230}, {"date": "2025-09-21T11:50:13.353000+00:00", "session_key": 9904, "driver_number": 1, "x": 918, "meeting_key": 1269, "z": -229, "y": 3188}, {"date": "2025-09-21T11:50:13.673000+00:00", "session_key": 9904, "driver_number": 1, "x": 732, "meeting_key": 1269, "z": -228, "y": 3119}, {"date": "2025-09-21T11:50:13.873000+00:00", "session_key": 9904, "driver_number": 1, "x": 613, "meeting_key": 1269, "z": -228, "y": 3075}, {"date": "2025-09-21T11:50:14.133000+00:00", "session_key": 9904, "driver_number": 1, "x": 429, "meeting_key": 1269, "z": -228, "y": 3006}, {"date": "2025-09-21T11:50:14.513000+00:00", "session_key": 9904, "driver_number": 1, "x": 214, "meeting_key": 1269, "z": -228, "y": 2925}, {"date": "2025-09-21T11:50:14.713000+00:00", "session_key": 9904, "driver_number": 1, "x": 85, "meeting_key": 1269, "z": -229, "y": 2876}, {"date": "2025-09-21T11:50:14.933000+00:00", "session_key": 9904, "driver_number": 1, "x": -59, "meeting_key": 1269, "z": -229, "y": 2822}, {"date": "2025-09-21T11:50:15.113000+00:00", "session_key": 9904, "driver_number": 1, "x": -179, "meeting_key": 1269, "z": -229, "y": 2777}, {"date": "2025-09-21T11:50:15.394000+00:00", "session_key": 9904, "driver_number": 1, "x": -365, "meeting_key": 1269, "z": -230, "y": 2708}, {"date": "2025-09-21T11:50:15.474000+00:00", "session_key": 9904, "driver_number": 1, "x": -420, "meeting_key": 1269, "z": -230, "y": 2687}, {"date": "2025-09-21T11:50:15.654000+00:00", "session_key": 9904, "driver_number": 1, "x": -544, "meeting_key": 1269, "z": -230, "y": 2640}, {"date": "2025-09-21T11:50:15.954000+00:00", "session_key": 9904, "driver_number": 1, "x": -837, "meeting_key": 1269, "z": -232, "y": 2524}, {"date": "2025-09-21T11:50:16.274000+00:00", "session_key": 9904, "driver_number": 1, "x": -977, "meeting_key": 1269, "z": -232, "y": 2465}, {"date": "2025-09-21T11:50:16.594000+00:00", "session_key": 9904, "driver_number": 1, "x": -1204, "meeting_key": 1269, "z": -232, "y": 2367}, {"date": "2025-09-21T11:50:16.774000+00:00", "session_key": 9904, "driver_number": 1, "x": -1333, "meeting_key": 1269, "z": -232, "y": 2311}, {"date": "2025-09-21T11:50:17.034000+00:00", "session_key": 9904, "driver_number": 1, "x": -1520, "meeting_key": 1269, "z": -232, "y": 2230}, {"date": "2025-09-21T11:50:17.214000+00:00", "session_key": 9904, "driver_number": 1, "x": -1651, "meeting_key": 1269, "z": -233, "y": 2174}, {"date": "2025-09-21T11:50:17.454000+00:00", "session_key": 9904, "driver_number": 1, "x": -1827, "meeting_key": 1269, "z": -233, "y": 2097}, {"date": "2025-09-21T11:50:17.534000+00:00", "session_key": 9904, "driver_number": 1, "x": -1886, "meeting_key": 1269, "z": -233, "y": 2072}, {"date": "2025-09-21T11:50:17.774000+00:00", "session_key": 9904, "driver_number": 1, "x": -2064, "meeting_key": 1269, "z": -233, "y": 1995}, {"date": "2025-09-21T11:50:18.034000+00:00", "session_key": 9904, "driver_number": 1, "x": -2319, "meeting_key": 1269, "z": -231, "y": 1885}, {"date": "2025-09-21T11:50:18.434000+00:00", "session_key": 9904, "driver_number": 1, "x": -2560, "meeting_key": 1269, "z": -231, "y": 1781}, {"date": "2025-09-21T11:50:18.634000+00:00", "session_key": 9904, "driver_number": 1, "x": -2773, "meeting_key": 1269, "z": -231, "y": 1690}, {"date": "2025-09-21T11:50:18.914000+00:00", "session_key": 9904, "driver_number": 1, "x": -2925, "meeting_key": 1269, "z": -230, "y": 1624}, {"date": "2025-09-21T11:50:19.233000+00:00", "session_key": 9904, "driver_number": 1, "x": -3261, "meeting_key": 1269, "z": -229, "y": 1478}, {"date": "2025-09-21T11:50:19.673000+00:00", "session_key": 9904, "driver_number": 1, "x": -3566, "meeting_key": 1269, "z": -227, "y": 1344}, {"date": "2025-09-21T11:50:20.013000+00:00", "session_key": 9904, "driver_number": 1, "x": -3763, "meeting_key": 1269, "z": -226, "y": 1256}, {"date": "2025-09-21T11:50:20.313000+00:00", "session_key": 9904, "driver_number": 1, "x": -3991, "meeting_key": 1269, "z": -225, "y": 1154}, {"date": "2025-09-21T11:50:20.453000+00:00", "session_key": 9904, "driver_number": 1, "x": -4098, "meeting_key": 1269, "z": -225, "y": 1107}, {"date": "2025-09-21T11:50:20.673000+00:00", "session_key": 9904, "driver_number": 1, "x": -4265, "meeting_key": 1269, "z": -224, "y": 1032}, {"date": "2025-09-21T11:50:20.913000+00:00", "session_key": 9904, "driver_number": 1, "x": -4534, "meeting_key": 1269, "z": -224, "y": 913}, {"date": "2025-09-21T11:50:21.313000+00:00", "session_key": 9904, "driver_number": 1, "x": -4729, "meeting_key": 1269, "z": -224, "y": 826}, {"date": "2025-09-21T11:50:21.373000+00:00", "session_key": 9904, "driver_number": 1, "x": -4767, "meeting_key": 1269, "z": -224, "y": 809}, {"date": "2025-09-21T11:50:21.653000+00:00", "session_key": 9904, "driver_number": 1, "x": -4931, "meeting_key": 1269, "z": -224, "y": 736}, {"date": "2025-09-21T11:50:21.874000+00:00", "session_key": 9904, "driver_number": 1, "x": -5042, "meeting_key": 1269, "z": -224, "y": 686}, {"date": "2025-09-21T11:50:22.054000+00:00", "session_key": 9904, "driver_number": 1, "x": -5163, "meeting_key": 1269, "z": -225, "y": 632}, {"date": "2025-09-21T11:50:22.334000+00:00", "session_key": 9904, "driver_number": 1, "x": -5275, "meeting_key": 1269, "z": -225, "y": 581}, {"date": "2025-09-21T11:50:22.474000+00:00", "session_key": 9904, "driver_number": 1, "x": -5325, "meeting_key": 1269, "z": -225, "y": 558}, {"date": "2025-09-21T11:50:22.674000+00:00", "session_key": 9904, "driver_number": 1, "x": -5389, "meeting_key": 1269, "z": -225, "y": 526}, {"date": "2025-09-21T11:50:22.874000+00:00", "session_key": 9904, "driver_number": 1, "x": -5446, "meeting_key": 1269, "z": -225, "y": 492}, {"date": "2025-09-21T11:50:23.134000+00:00", "session_key": 9904, "driver_number": 1, "x": -5507, "meeting_key": 1269, "z": -226, "y": 446}, {"date": "2025-09-21T11:50:23.354000+00:00", "session_key": 9904, "driver_number": 1, "x": -5548, "meeting_key": 1269, "z": -226, "y": 402}, {"date": "2025-09-21T11:50:23.454000+00:00", "session_key": 9904, "driver_number": 1, "x": -5562, "meeting_key": 1269, "z": -226, "y": 380}, {"date": "2025-09-21T11:50:23.734000+00:00", "session_key": 9904, "driver_number": 1, "x": -5585, "meeting_key": 1269, "z": -226, "y": 312}, {"date": "2025-09-21T11:50:23.954000+00:00", "session_key": 9904, "driver_number": 1, "x": -5583, "meeting_key": 1269, "z": -225, "y": 253}, {"date": "2025-09-21T11:50:24.134000+00:00", "session_key": 9904, "driver_number": 1, "x": -5571, "meeting_key": 1269, "z": -225, "y": 203}, {"date": "2025-09-21T11:50:24.374000+00:00", "session_key": 9904, "driver_number": 1, "x": -5546, "meeting_key": 1269, "z": -226, "y": 135}, {"date": "2025-09-21T11:50:24.494000+00:00", "session_key": 9904, "driver_number": 1, "x": -5530, "meeting_key": 1269, "z": -226, "y": 101}, {"date": "2025-09-21T11:50:24.834000+00:00", "session_key": 9904, "driver_number": 1, "x": -5481, "meeting_key": 1269, "z": -226, "y": 1}, {"date": "2025-09-21T11:50:25.014000+00:00", "session_key": 9904, "driver_number": 1, "x": -5452, "meeting_key": 1269, "z": -227, "y": -54}, {"date": "2025-09-21T11:50:25.194000+00:00", "session_key": 9904, "driver_number": 1, "x": -5423, "meeting_key": 1269, "z": -227, "y": -114}, {"date": "2025-09-21T11:50:25.414000+00:00", "session_key": 9904, "driver_number": 1, "x": -5387, "meeting_key": 1269, "z": -227, "y": -194}, {"date": "2025-09-21T11:50:25.494000+00:00", "session_key": 9904, "driver_number": 1, "x": -5375, "meeting_key": 1269, "z": -227, "y": -224}, {"date": "2025-09-21T11:50:25.674000+00:00", "session_key": 9904, "driver_number": 1, "x": -5348, "meeting_key": 1269, "z": -228, "y": -298}, {"date": "2025-09-21T11:50:25.973000+00:00", "session_key": 9904, "driver_number": 1, "x": -5305, "meeting_key": 1269, "z": -228, "y": -431}, {"date": "2025-09-21T11:50:26.193000+00:00", "session_key": 9904, "driver_number": 1, "x": -5272, "meeting_key": 1269, "z": -228, "y": -535}, {"date": "2025-09-21T11:50:26.353000+00:00", "session_key": 9904, "driver_number": 1, "x": -5246, "meeting_key": 1269, "z": -229, "y": -611}, {"date": "2025-09-21T11:50:26.653000+00:00", "session_key": 9904, "driver_number": 1, "x": -5190, "meeting_key": 1269, "z": -230, "y": -756}, {"date": "2025-09-21T11:50:26.853000+00:00", "session_key": 9904, "driver_number": 1, "x": -5146, "meeting_key": 1269, "z": -231, "y": -856}, {"date": "2025-09-21T11:50:27.093000+00:00", "session_key": 9904, "driver_number": 1, "x": -5080, "meeting_key": 1269, "z": -231, "y": -1000}, {"date": "2025-09-21T11:50:27.333000+00:00", "session_key": 9904, "driver_number": 1, "x": -5033, "meeting_key": 1269, "z": -232, "y": -1099}, {"date": "2025-09-21T11:50:27.673000+00:00", "session_key": 9904, "driver_number": 1, "x": -4965, "meeting_key": 1269, "z": -233, "y": -1247}, {"date": "2025-09-21T11:50:27.853000+00:00", "session_key": 9904, "driver_number": 1, "x": -4936, "meeting_key": 1269, "z": -233, "y": -1315}, {"date": "2025-09-21T11:50:28.113000+00:00", "session_key": 9904, "driver_number": 1, "x": -4891, "meeting_key": 1269, "z": -233, "y": -1432}, {"date": "2025-09-21T11:50:28.514000+00:00", "session_key": 9904, "driver_number": 1, "x": -4862, "meeting_key": 1269, "z": -234, "y": -1529}, {"date": "2025-09-21T11:50:28.654000+00:00", "session_key": 9904, "driver_number": 1, "x": -4854, "meeting_key": 1269, "z": -234, "y": -1568}, {"date": "2025-09-21T11:50:28.934000+00:00", "session_key": 9904, "driver_number": 1, "x": -4849, "meeting_key": 1269, "z": -234, "y": -1667}, {"date": "2025-09-21T11:50:29.314000+00:00", "session_key": 9904, "driver_number": 1, "x": -4866, "meeting_key": 1269, "z": -234, "y": -1734}, {"date": "2025-09-21T11:50:29.454000+00:00", "session_key": 9904, "driver_number": 1, "x": -4882, "meeting_key": 1269, "z": -234, "y": -1764}, {"date": "2025-09-21T11:50:29.754000+00:00", "session_key": 9904, "driver_number": 1, "x": -4951, "meeting_key": 1269, "z": -235, "y": -1837}, {"date": "2025-09-21T11:50:30.074000+00:00", "session_key": 9904, "driver_number": 1, "x": -4993, "meeting_key": 1269, "z": -235, "y": -1864}, {"date": "2025-09-21T11:50:30.294000+00:00", "session_key": 9904, "driver_number": 1, "x": -5044, "meeting_key": 1269, "z": -235, "y": -1892}, {"date": "2025-09-21T11:50:30.574000+00:00", "session_key": 9904, "driver_number": 1, "x": -5115, "meeting_key": 1269, "z": -235, "y": -1925}, {"date": "2025-09-21T11:50:30.794000+00:00", "session_key": 9904, "driver_number": 1, "x": -5207, "meeting_key": 1269, "z": -236, "y": -1962}, {"date": "2025-09-21T11:50:31.094000+00:00", "session_key": 9904, "driver_number": 1, "x": -5272, "meeting_key": 1269, "z": -236, "y": -1987}, {"date": "2025-09-21T11:50:31.394000+00:00", "session_key": 9904, "driver_number": 1, "x": -5368, "meeting_key": 1269, "z": -236, "y": -2021}, {"date": "2025-09-21T11:50:31.554000+00:00", "session_key": 9904, "driver_number": 1, "x": -5463, "meeting_key": 1269, "z": -237, "y": -2057}, {"date": "2025-09-21T11:50:31.894000+00:00", "session_key": 9904, "driver_number": 1, "x": -5571, "meeting_key": 1269, "z": -237, "y": -2101}, {"date": "2025-09-21T11:50:32.214000+00:00", "session_key": 9904, "driver_number": 1, "x": -5732, "meeting_key": 1269, "z": -238, "y": -2172}, {"date": "2025-09-21T11:50:32.593000+00:00", "session_key": 9904, "driver_number": 1, "x": -5895, "meeting_key": 1269, "z": -239, "y": -2244}, {"date": "2025-09-21T11:50:32.793000+00:00", "session_key": 9904, "driver_number": 1, "x": -6067, "meeting_key": 1269, "z": -239, "y": -2315}, {"date": "2025-09-21T11:50:33.073000+00:00", "session_key": 9904, "driver_number": 1, "x": -6141, "meeting_key": 1269, "z": -240, "y": -2346}, {"date": "2025-09-21T11:50:33.353000+00:00", "session_key": 9904, "driver_number": 1, "x": -6294, "meeting_key": 1269, "z": -240, "y": -2414}, {"date": "2025-09-21T11:50:33.573000+00:00", "session_key": 9904, "driver_number": 1, "x": -6468, "meeting_key": 1269, "z": -240, "y": -2503}, {"date": "2025-09-21T11:50:33.873000+00:00", "session_key": 9904, "driver_number": 1, "x": -6577, "meeting_key": 1269, "z": -241, "y": -2565}, {"date": "2025-09-21T11:50:34.193000+00:00", "session_key": 9904, "driver_number": 1, "x": -6753, "meeting_key": 1269, "z": -240, "y": -2670}, {"date": "2025-09-21T11:50:34.393000+00:00", "session_key": 9904, "driver_number": 1, "x": -6864, "meeting_key": 1269, "z": -240, "y": -2737}, {"date": "2025-09-21T11:50:34.653000+00:00", "session_key": 9904, "driver_number": 1, "x": -7007, "meeting_key": 1269, "z": -240, "y": -2823}, {"date": "2025-09-21T11:50:34.853000+00:00", "session_key": 9904, "driver_number": 1, "x": -7166, "meeting_key": 1269, "z": -239, "y": -2913}, {"date": "2025-09-21T11:50:35.094000+00:00", "session_key": 9904, "driver_number": 1, "x": -7230, "meeting_key": 1269, "z": -239, "y": -2947}, {"date": "2025-09-21T11:50:35.354000+00:00", "session_key": 9904, "driver_number": 1, "x": -7346, "meeting_key": 1269, "z": -240, "y": -3010}, {"date": "2025-09-21T11:50:35.514000+00:00", "session_key": 9904, "driver_number": 1, "x": -7408, "meeting_key": 1269, "z": -240, "y": -3047}, {"date": "2025-09-21T11:50:35.814000+00:00", "session_key": 9904, "driver_number": 1, "x": -7547, "meeting_key": 1269, "z": -240, "y": -3141}, {"date": "2025-09-21T11:50:36.174000+00:00", "session_key": 9904, "driver_number": 1, "x": -7611, "meeting_key": 1269, "z": -240, "y": -3197}, {"date": "2025-09-21T11:50:36.414000+00:00", "session_key": 9904, "driver_number": 1, "x": -7662, "meeting_key": 1269, "z": -241, "y": -3253}, {"date": "2025-09-21T11:50:36.554000+00:00", "session_key": 9904, "driver_number": 1, "x": -7687, "meeting_key": 1269, "z": -241, "y": -3287}, {"date": "2025-09-21T11:50:36.754000+00:00", "session_key": 9904, "driver_number": 1, "x": -7716, "meeting_key": 1269, "z": -241, "y": -3337}, {"date": "2025-09-21T11:50:36.994000+00:00", "session_key": 9904, "driver_number": 1, "x": -7738, "meeting_key": 1269, "z": -241, "y": -3399}, {"date": "2025-09-21T11:50:37.234000+00:00", "session_key": 9904, "driver_number": 1, "x": -7745, "meeting_key": 1269, "z": -242, "y": -3462}, {"date": "2025-09-21T11:50:37.414000+00:00", "session_key": 9904, "driver_number": 1, "x": -7741, "meeting_key": 1269, "z": -242, "y": -3508}, {"date": "2025-09-21T11:50:37.654000+00:00", "session_key": 9904, "driver_number": 1, "x": -7723, "meeting_key": 1269, "z": -242, "y": -3568}, {"date": "2025-09-21T11:50:37.854000+00:00", "session_key": 9904, "driver_number": 1, "x": -7701, "meeting_key": 1269, "z": -242, "y": -3619}, {"date": "2025-09-21T11:50:38.114000+00:00", "session_key": 9904, "driver_number": 1, "x": -7660, "meeting_key": 1269, "z": -242, "y": -3700}, {"date": "2025-09-21T11:50:38.494000+00:00", "session_key": 9904, "driver_number": 1, "x": -7626, "meeting_key": 1269, "z": -242, "y": -3777}, {"date": "2025-09-21T11:50:38.714000+00:00", "session_key": 9904, "driver_number": 1, "x": -7608, "meeting_key": 1269, "z": -242, "y": -3850}, {"date": "2025-09-21T11:50:39.033000+00:00", "session_key": 9904, "driver_number": 1, "x": -7610, "meeting_key": 1269, "z": -241, "y": -3899}, {"date": "2025-09-21T11:50:39.373000+00:00", "session_key": 9904, "driver_number": 1, "x": -7654, "meeting_key": 1269, "z": -241, "y": -3988}, {"date": "2025-09-21T11:50:39.693000+00:00", "session_key": 9904, "driver_number": 1, "x": -7698, "meeting_key": 1269, "z": -241, "y": -4033}, {"date": "2025-09-21T11:50:39.993000+00:00", "session_key": 9904, "driver_number": 1, "x": -7775, "meeting_key": 1269, "z": -240, "y": -4092}, {"date": "2025-09-21T11:50:40.253000+00:00", "session_key": 9904, "driver_number": 1, "x": -7831, "meeting_key": 1269, "z": -240, "y": -4129}, {"date": "2025-09-21T11:50:40.453000+00:00", "session_key": 9904, "driver_number": 1, "x": -7887, "meeting_key": 1269, "z": -240, "y": -4164}, {"date": "2025-09-21T11:50:40.653000+00:00", "session_key": 9904, "driver_number": 1, "x": -7948, "meeting_key": 1269, "z": -239, "y": -4202}, {"date": "2025-09-21T11:50:40.973000+00:00", "session_key": 9904, "driver_number": 1, "x": -8112, "meeting_key": 1269, "z": -239, "y": -4309}, {"date": "2025-09-21T11:50:41.353000+00:00", "session_key": 9904, "driver_number": 1, "x": -8255, "meeting_key": 1269, "z": -238, "y": -4419}, {"date": "2025-09-21T11:50:41.654000+00:00", "session_key": 9904, "driver_number": 1, "x": -8332, "meeting_key": 1269, "z": -238, "y": -4480}, {"date": "2025-09-21T11:50:41.994000+00:00", "session_key": 9904, "driver_number": 1, "x": -8470, "meeting_key": 1269, "z": -237, "y": -4589}, {"date": "2025-09-21T11:50:42.194000+00:00", "session_key": 9904, "driver_number": 1, "x": -8618, "meeting_key": 1269, "z": -237, "y": -4702}, {"date": "2025-09-21T11:50:42.474000+00:00", "session_key": 9904, "driver_number": 1, "x": -8682, "meeting_key": 1269, "z": -237, "y": -4750}, {"date": "2025-09-21T11:50:42.834000+00:00", "session_key": 9904, "driver_number": 1, "x": -8853, "meeting_key": 1269, "z": -237, "y": -4878}, {"date": "2025-09-21T11:50:43.034000+00:00", "session_key": 9904, "driver_number": 1, "x": -8951, "meeting_key": 1269, "z": -237, "y": -4952}, {"date": "2025-09-21T11:50:43.254000+00:00", "session_key": 9904, "driver_number": 1, "x": -9061, "meeting_key": 1269, "z": -237, "y": -5036}, {"date": "2025-09-21T11:50:43.474000+00:00", "session_key": 9904, "driver_number": 1, "x": -9194, "meeting_key": 1269, "z": -236, "y": -5137}, {"date": "2025-09-21T11:50:43.734000+00:00", "session_key": 9904, "driver_number": 1, "x": -9308, "meeting_key": 1269, "z": -236, "y": -5224}, {"date": "2025-09-21T11:50:43.914000+00:00", "session_key": 9904, "driver_number": 1, "x": -9403, "meeting_key": 1269, "z": -236, "y": -5297}, {"date": "2025-09-21T11:50:44.254000+00:00", "session_key": 9904, "driver_number": 1, "x": -9585, "meeting_key": 1269, "z": -236, "y": -5435}, {"date": "2025-09-21T11:50:44.454000+00:00", "session_key": 9904, "driver_number": 1, "x": -9693, "meeting_key": 1269, "z": -235, "y": -5518}, {"date": "2025-09-21T11:50:44.574000+00:00", "session_key": 9904, "driver_number": 1, "x": -9759, "meeting_key": 1269, "z": -235, "y": -5568}, {"date": "2025-09-21T11:50:44.734000+00:00", "session_key": 9904, "driver_number": 1, "x": -9847, "meeting_key": 1269, "z": -235, "y": -5635}, {"date": "2025-09-21T11:50:45.054000+00:00", "session_key": 9904, "driver_number": 1, "x": -10016, "meeting_key": 1269, "z": -235, "y": -5762}, {"date": "2025-09-21T11:50:45.214000+00:00", "session_key": 9904, "driver_number": 1, "x": -10092, "meeting_key": 1269, "z": -235, "y": -5819}, {"date": "2025-09-21T11:50:45.394000+00:00", "session_key": 9904, "driver_number": 1, "x": -10173, "meeting_key": 1269, "z": -236, "y": -5880}, {"date": "2025-09-21T11:50:45.713000+00:00", "session_key": 9904, "driver_number": 1, "x": -10294, "meeting_key": 1269, "z": -234, "y": -5975}, {"date": "2025-09-21T11:50:45.873000+00:00", "session_key": 9904, "driver_number": 1, "x": -10389, "meeting_key": 1269, "z": -234, "y": -6052}, {"date": "2025-09-21T11:50:46.153000+00:00", "session_key": 9904, "driver_number": 1, "x": -10427, "meeting_key": 1269, "z": -235, "y": -6083}, {"date": "2025-09-21T11:50:46.413000+00:00", "session_key": 9904, "driver_number": 1, "x": -10491, "meeting_key": 1269, "z": -237, "y": -6133}, {"date": "2025-09-21T11:50:46.593000+00:00", "session_key": 9904, "driver_number": 1, "x": -10532, "meeting_key": 1269, "z": -237, "y": -6162}, {"date": "2025-09-21T11:50:46.753000+00:00", "session_key": 9904, "driver_number": 1, "x": -10567, "meeting_key": 1269, "z": -237, "y": -6184}, {"date": "2025-09-21T11:50:47.013000+00:00", "session_key": 9904, "driver_number": 1, "x": -10620, "meeting_key": 1269, "z": -237, "y": -6213}, {"date": "2025-09-21T11:50:47.353000+00:00", "session_key": 9904, "driver_number": 1, "x": -10700, "meeting_key": 1269, "z": -236, "y": -6238}, {"date": "2025-09-21T11:50:47.633000+00:00", "session_key": 9904, "driver_number": 1, "x": -10737, "meeting_key": 1269, "z": -236, "y": -6238}, {"date": "2025-09-21T11:50:47.793000+00:00", "session_key": 9904, "driver_number": 1, "x": -10765, "meeting_key": 1269, "z": -234, "y": -6231}, {"date": "2025-09-21T11:50:48.113000+00:00", "session_key": 9904, "driver_number": 1, "x": -10833, "meeting_key": 1269, "z": -234, "y": -6181}, {"date": "2025-09-21T11:50:48.534000+00:00", "session_key": 9904, "driver_number": 1, "x": -10883, "meeting_key": 1269, "z": -233, "y": -6105}, {"date": "2025-09-21T11:50:48.814000+00:00", "session_key": 9904, "driver_number": 1, "x": -10900, "meeting_key": 1269, "z": -232, "y": -6071}, {"date": "2025-09-21T11:50:49.174000+00:00", "session_key": 9904, "driver_number": 1, "x": -10938, "meeting_key": 1269, "z": -231, "y": -5978}, {"date": "2025-09-21T11:50:49.554000+00:00", "session_key": 9904, "driver_number": 1, "x": -10973, "meeting_key": 1269, "z": -231, "y": -5877}, {"date": "2025-09-21T11:50:49.754000+00:00", "session_key": 9904, "driver_number": 1, "x": -11004, "meeting_key": 1269, "z": -230, "y": -5780}, {"date": "2025-09-21T11:50:50.054000+00:00", "session_key": 9904, "driver_number": 1, "x": -11025, "meeting_key": 1269, "z": -230, "y": -5710}, {"date": "2025-09-21T11:50:50.414000+00:00", "session_key": 9904, "driver_number": 1, "x": -11075, "meeting_key": 1269, "z": -229, "y": -5540}, {"date": "2025-09-21T11:50:50.654000+00:00", "session_key": 9904, "driver_number": 1, "x": -11098, "meeting_key": 1269, "z": -228, "y": -5462}, {"date": "2025-09-21T11:50:50.954000+00:00", "session_key": 9904, "driver_number": 1, "x": -11159, "meeting_key": 1269, "z": -227, "y": -5259}, {"date": "2025-09-21T11:50:51.134000+00:00", "session_key": 9904, "driver_number": 1, "x": -11185, "meeting_key": 1269, "z": -226, "y": -5175}, {"date": "2025-09-21T11:50:51.394000+00:00", "session_key": 9904, "driver_number": 1, "x": -11246, "meeting_key": 1269, "z": -224, "y": -4976}, {"date": "2025-09-21T11:50:51.734000+00:00", "session_key": 9904, "driver_number": 1, "x": -11276, "meeting_key": 1269, "z": -223, "y": -4873}, {"date": "2025-09-21T11:50:52.074000+00:00", "session_key": 9904, "driver_number": 1, "x": -11332, "meeting_key": 1269, "z": -221, "y": -4685}, {"date": "2025-09-21T11:50:52.453000+00:00", "session_key": 9904, "driver_number": 1, "x": -11369, "meeting_key": 1269, "z": -220, "y": -4560}, {"date": "2025-09-21T11:50:52.573000+00:00", "session_key": 9904, "driver_number": 1, "x": -11382, "meeting_key": 1269, "z": -219, "y": -4517}, {"date": "2025-09-21T11:50:52.793000+00:00", "session_key": 9904, "driver_number": 1, "x": -11420, "meeting_key": 1269, "z": -217, "y": -4407}, {"date": "2025-09-21T11:50:53.153000+00:00", "session_key": 9904, "driver_number": 1, "x": -11461, "meeting_key": 1269, "z": -215, "y": -4355}, {"date": "2025-09-21T11:50:53.393000+00:00", "session_key": 9904, "driver_number": 1, "x": -11532, "meeting_key": 1269, "z": -212, "y": -4318}, {"date": "2025-09-21T11:50:53.713000+00:00", "session_key": 9904, "driver_number": 1, "x": -11629, "meeting_key": 1269, "z": -206, "y": -4276}, {"date": "2025-09-21T11:50:53.793000+00:00", "session_key": 9904, "driver_number": 1, "x": -11654, "meeting_key": 1269, "z": -203, "y": -4266}, {"date": "2025-09-21T11:50:54.133000+00:00", "session_key": 9904, "driver_number": 1, "x": -11769, "meeting_key": 1269, "z": -193, "y": -4226}, {"date": "2025-09-21T11:50:54.333000+00:00", "session_key": 9904, "driver_number": 1, "x": -11843, "meeting_key": 1269, "z": -183, "y": -4207}, {"date": "2025-09-21T11:50:54.493000+00:00", "session_key": 9904, "driver_number": 1, "x": -11958, "meeting_key": 1269, "z": -170, "y": -4190}, {"date": "2025-09-21T11:50:54.834000+00:00", "session_key": 9904, "driver_number": 1, "x": -12033, "meeting_key": 1269, "z": -161, "y": -4183}, {"date": "2025-09-21T11:50:55.054000+00:00", "session_key": 9904, "driver_number": 1, "x": -12153, "meeting_key": 1269, "z": -147, "y": -4174}, {"date": "2025-09-21T11:50:55.414000+00:00", "session_key": 9904, "driver_number": 1, "x": -12219, "meeting_key": 1269, "z": -142, "y": -4166}, {"date": "2025-09-21T11:50:55.754000+00:00", "session_key": 9904, "driver_number": 1, "x": -12312, "meeting_key": 1269, "z": -140, "y": -4145}, {"date": "2025-09-21T11:50:55.994000+00:00", "session_key": 9904, "driver_number": 1, "x": -12389, "meeting_key": 1269, "z": -142, "y": -4113}, {"date": "2025-09-21T11:50:56.254000+00:00", "session_key": 9904, "driver_number": 1, "x": -12428, "meeting_key": 1269, "z": -142, "y": -4089}, {"date": "2025-09-21T11:50:56.454000+00:00", "session_key": 9904, "driver_number": 1, "x": -12466, "meeting_key": 1269, "z": -143, "y": -4057}, {"date": "2025-09-21T11:50:56.674000+00:00", "session_key": 9904, "driver_number": 1, "x": -12499, "meeting_key": 1269, "z": -144, "y": -4012}, {"date": "2025-09-21T11:50:56.894000+00:00", "session_key": 9904, "driver_number": 1, "x": -12521, "meeting_key": 1269, "z": -147, "y": -3957}, {"date": "2025-09-21T11:50:57.094000+00:00", "session_key": 9904, "driver_number": 1, "x": -12530, "meeting_key": 1269, "z": -150, "y": -3897}, {"date": "2025-09-21T11:50:57.454000+00:00", "session_key": 9904, "driver_number": 1, "x": -12537, "meeting_key": 1269, "z": -159, "y": -3738}, {"date": "2025-09-21T11:50:57.754000+00:00", "session_key": 9904, "driver_number": 1, "x": -12550, "meeting_key": 1269, "z": -161, "y": -3688}, {"date": "2025-09-21T11:50:57.934000+00:00", "session_key": 9904, "driver_number": 1, "x": -12576, "meeting_key": 1269, "z": -161, "y": -3646}, {"date": "2025-09-21T11:50:58.174000+00:00", "session_key": 9904, "driver_number": 1, "x": -12631, "meeting_key": 1269, "z": -160, "y": -3609}, {"date": "2025-09-21T11:50:58.414000+00:00", "session_key": 9904, "driver_number": 1, "x": -12701, "meeting_key": 1269, "z": -158, "y": -3591}, {"date": "2025-09-21T11:50:58.574000+00:00", "session_key": 9904, "driver_number": 1, "x": -12751, "meeting_key": 1269, "z": -157, "y": -3586}, {"date": "2025-09-21T11:50:59.473000+00:00", "session_key": 9904, "driver_number": 1, "x": -13115, "meeting_key": 1269, "z": -130, "y": -3624}, {"date": "2025-09-21T11:50:59.853000+00:00", "session_key": 9904, "driver_number": 1, "x": -13235, "meeting_key": 1269, "z": -121, "y": -3655}, {"date": "2025-09-21T11:51:00.293000+00:00", "session_key": 9904, "driver_number": 1, "x": -13418, "meeting_key": 1269, "z": -107, "y": -3724}, {"date": "2025-09-21T11:51:00.533000+00:00", "session_key": 9904, "driver_number": 1, "x": -13510, "meeting_key": 1269, "z": -101, "y": -3765}, {"date": "2025-09-21T11:51:00.833000+00:00", "session_key": 9904, "driver_number": 1, "x": -13710, "meeting_key": 1269, "z": -86, "y": -3856}, {"date": "2025-09-21T11:51:01.314000+00:00", "session_key": 9904, "driver_number": 1, "x": -13940, "meeting_key": 1269, "z": -70, "y": -3952}, {"date": "2025-09-21T11:51:01.654000+00:00", "session_key": 9904, "driver_number": 1, "x": -14083, "meeting_key": 1269, "z": -61, "y": -4014}, {"date": "2025-09-21T11:51:01.834000+00:00", "session_key": 9904, "driver_number": 1, "x": -14183, "meeting_key": 1269, "z": -55, "y": -4060}, {"date": "2025-09-21T11:51:02.034000+00:00", "session_key": 9904, "driver_number": 1, "x": -14295, "meeting_key": 1269, "z": -47, "y": -4116}, {"date": "2025-09-21T11:51:02.354000+00:00", "session_key": 9904, "driver_number": 1, "x": -14477, "meeting_key": 1269, "z": -39, "y": -4211}, {"date": "2025-09-21T11:51:02.574000+00:00", "session_key": 9904, "driver_number": 1, "x": -14666, "meeting_key": 1269, "z": -31, "y": -4307}, {"date": "2025-09-21T11:51:02.814000+00:00", "session_key": 9904, "driver_number": 1, "x": -14750, "meeting_key": 1269, "z": -29, "y": -4349}, {"date": "2025-09-21T11:51:03.074000+00:00", "session_key": 9904, "driver_number": 1, "x": -14911, "meeting_key": 1269, "z": -23, "y": -4427}, {"date": "2025-09-21T11:51:03.334000+00:00", "session_key": 9904, "driver_number": 1, "x": -15122, "meeting_key": 1269, "z": -18, "y": -4538}, {"date": "2025-09-21T11:51:03.774000+00:00", "session_key": 9904, "driver_number": 1, "x": -15385, "meeting_key": 1269, "z": -11, "y": -4687}, {"date": "2025-09-21T11:51:04.194000+00:00", "session_key": 9904, "driver_number": 1, "x": -15665, "meeting_key": 1269, "z": -2, "y": -4851}, {"date": "2025-09-21T11:51:04.474000+00:00", "session_key": 9904, "driver_number": 1, "x": -15795, "meeting_key": 1269, "z": 2, "y": -4924}, {"date": "2025-09-21T11:51:04.694000+00:00", "session_key": 9904, "driver_number": 1, "x": -15942, "meeting_key": 1269, "z": 7, "y": -5002}, {"date": "2025-09-21T11:51:04.954000+00:00", "session_key": 9904, "driver_number": 1, "x": -16107, "meeting_key": 1269, "z": 16, "y": -5103}, {"date": "2025-09-21T11:51:05.174000+00:00", "session_key": 9904, "driver_number": 1, "x": -16220, "meeting_key": 1269, "z": 20, "y": -5208}, {"date": "2025-09-21T11:51:05.373000+00:00", "session_key": 9904, "driver_number": 1, "x": -16305, "meeting_key": 1269, "z": 21, "y": -5333}, {"date": "2025-09-21T11:51:05.553000+00:00", "session_key": 9904, "driver_number": 1, "x": -16367, "meeting_key": 1269, "z": 21, "y": -5459}, {"date": "2025-09-21T11:51:05.773000+00:00", "session_key": 9904, "driver_number": 1, "x": -16430, "meeting_key": 1269, "z": 20, "y": -5620}, {"date": "2025-09-21T11:51:05.933000+00:00", "session_key": 9904, "driver_number": 1, "x": -16469, "meeting_key": 1269, "z": 19, "y": -5739}, {"date": "2025-09-21T11:51:06.113000+00:00", "session_key": 9904, "driver_number": 1, "x": -16510, "meeting_key": 1269, "z": 19, "y": -5874}, {"date": "2025-09-21T11:51:06.373000+00:00", "session_key": 9904, "driver_number": 1, "x": -16567, "meeting_key": 1269, "z": 18, "y": -6070}, {"date": "2025-09-21T11:51:06.553000+00:00", "session_key": 9904, "driver_number": 1, "x": -16608, "meeting_key": 1269, "z": 17, "y": -6206}, {"date": "2025-09-21T11:51:06.793000+00:00", "session_key": 9904, "driver_number": 1, "x": -16666, "meeting_key": 1269, "z": 16, "y": -6389}, {"date": "2025-09-21T11:51:07.073000+00:00", "session_key": 9904, "driver_number": 1, "x": -16771, "meeting_key": 1269, "z": 14, "y": -6711}, {"date": "2025-09-21T11:51:07.413000+00:00", "session_key": 9904, "driver_number": 1, "x": -16821, "meeting_key": 1269, "z": 13, "y": -6878}, {"date": "2025-09-21T11:51:07.713000+00:00", "session_key": 9904, "driver_number": 1, "x": -16886, "meeting_key": 1269, "z": 11, "y": -7194}, {"date": "2025-09-21T11:51:07.773000+00:00", "session_key": 9904, "driver_number": 1, "x": -16892, "meeting_key": 1269, "z": 10, "y": -7243}, {"date": "2025-09-21T11:51:08.114000+00:00", "session_key": 9904, "driver_number": 1, "x": -16908, "meeting_key": 1269, "z": 7, "y": -7552}, {"date": "2025-09-21T11:51:08.434000+00:00", "session_key": 9904, "driver_number": 1, "x": -16900, "meeting_key": 1269, "z": 5, "y": -7782}, {"date": "2025-09-21T11:51:08.754000+00:00", "session_key": 9904, "driver_number": 1, "x": -16882, "meeting_key": 1269, "z": 3, "y": -8043}, {"date": "2025-09-21T11:51:08.854000+00:00", "session_key": 9904, "driver_number": 1, "x": -16876, "meeting_key": 1269, "z": 2, "y": -8125}, {"date": "2025-09-21T11:51:09.054000+00:00", "session_key": 9904, "driver_number": 1, "x": -16864, "meeting_key": 1269, "z": 0, "y": -8286}, {"date": "2025-09-21T11:51:09.234000+00:00", "session_key": 9904, "driver_number": 1, "x": -16852, "meeting_key": 1269, "z": 0, "y": -8427}, {"date": "2025-09-21T11:51:09.494000+00:00", "session_key": 9904, "driver_number": 1, "x": -16832, "meeting_key": 1269, "z": -4, "y": -8692}, {"date": "2025-09-21T11:51:09.834000+00:00", "session_key": 9904, "driver_number": 1, "x": -16832, "meeting_key": 1269, "z": -7, "y": -8825}, {"date": "2025-09-21T11:51:10.014000+00:00", "session_key": 9904, "driver_number": 1, "x": -16837, "meeting_key": 1269, "z": -11, "y": -8932}, {"date": "2025-09-21T11:51:10.254000+00:00", "session_key": 9904, "driver_number": 1, "x": -16848, "meeting_key": 1269, "z": -15, "y": -9058}, {"date": "2025-09-21T11:51:10.534000+00:00", "session_key": 9904, "driver_number": 1, "x": -16860, "meeting_key": 1269, "z": -20, "y": -9182}, {"date": "2025-09-21T11:51:10.714000+00:00", "session_key": 9904, "driver_number": 1, "x": -16865, "meeting_key": 1269, "z": -22, "y": -9252}, {"date": "2025-09-21T11:51:10.914000+00:00", "session_key": 9904, "driver_number": 1, "x": -16870, "meeting_key": 1269, "z": -24, "y": -9325}, {"date": "2025-09-21T11:51:11.094000+00:00", "session_key": 9904, "driver_number": 1, "x": -16871, "meeting_key": 1269, "z": -26, "y": -9382}, {"date": "2025-09-21T11:51:11.354000+00:00", "session_key": 9904, "driver_number": 1, "x": -16869, "meeting_key": 1269, "z": -28, "y": -9458}, {"date": "2025-09-21T11:51:11.654000+00:00", "session_key": 9904, "driver_number": 1, "x": -16855, "meeting_key": 1269, "z": -30, "y": -9534}, {"date": "2025-09-21T11:51:11.834000+00:00", "session_key": 9904, "driver_number": 1, "x": -16837, "meeting_key": 1269, "z": -33, "y": -9573}, {"date": "2025-09-21T11:51:12.053000+00:00", "session_key": 9904, "driver_number": 1, "x": -16793, "meeting_key": 1269, "z": -37, "y": -9621}, {"date": "2025-09-21T11:51:12.393000+00:00", "session_key": 9904, "driver_number": 1, "x": -16708, "meeting_key": 1269, "z": -45, "y": -9669}, {"date": "2025-09-21T11:51:12.873000+00:00", "session_key": 9904, "driver_number": 1, "x": -16593, "meeting_key": 1269, "z": -57, "y": -9724}, {"date": "2025-09-21T11:51:13.213000+00:00", "session_key": 9904, "driver_number": 1, "x": -16521, "meeting_key": 1269, "z": -64, "y": -9761}, {"date": "2025-09-21T11:51:13.433000+00:00", "session_key": 9904, "driver_number": 1, "x": -16454, "meeting_key": 1269, "z": -71, "y": -9797}, {"date": "2025-09-21T11:51:13.633000+00:00", "session_key": 9904, "driver_number": 1, "x": -16387, "meeting_key": 1269, "z": -78, "y": -9832}, {"date": "2025-09-21T11:51:13.933000+00:00", "session_key": 9904, "driver_number": 1, "x": -16277, "meeting_key": 1269, "z": -89, "y": -9890}, {"date": "2025-09-21T11:51:14.113000+00:00", "session_key": 9904, "driver_number": 1, "x": -16204, "meeting_key": 1269, "z": -97, "y": -9927}, {"date": "2025-09-21T11:51:14.273000+00:00", "session_key": 9904, "driver_number": 1, "x": -16137, "meeting_key": 1269, "z": -104, "y": -9961}, {"date": "2025-09-21T11:51:14.433000+00:00", "session_key": 9904, "driver_number": 1, "x": -16066, "meeting_key": 1269, "z": -111, "y": -9996}, {"date": "2025-09-21T11:51:14.714000+00:00", "session_key": 9904, "driver_number": 1, "x": -15936, "meeting_key": 1269, "z": -125, "y": -10060}, {"date": "2025-09-21T11:51:14.774000+00:00", "session_key": 9904, "driver_number": 1, "x": -15907, "meeting_key": 1269, "z": -128, "y": -10075}, {"date": "2025-09-21T11:51:15.114000+00:00", "session_key": 9904, "driver_number": 1, "x": -15740, "meeting_key": 1269, "z": -145, "y": -10157}, {"date": "2025-09-21T11:51:15.294000+00:00", "session_key": 9904, "driver_number": 1, "x": -15575, "meeting_key": 1269, "z": -161, "y": -10243}, {"date": "2025-09-21T11:51:15.774000+00:00", "session_key": 9904, "driver_number": 1, "x": -15391, "meeting_key": 1269, "z": -179, "y": -10344}, {"date": "2025-09-21T11:51:15.974000+00:00", "session_key": 9904, "driver_number": 1, "x": -15225, "meeting_key": 1269, "z": -192, "y": -10441}, {"date": "2025-09-21T11:51:16.314000+00:00", "session_key": 9904, "driver_number": 1, "x": -15032, "meeting_key": 1269, "z": -202, "y": -10555}, {"date": "2025-09-21T11:51:16.674000+00:00", "session_key": 9904, "driver_number": 1, "x": -14880, "meeting_key": 1269, "z": -207, "y": -10639}, {"date": "2025-09-21T11:51:16.994000+00:00", "session_key": 9904, "driver_number": 1, "x": -14608, "meeting_key": 1269, "z": -214, "y": -10779}, {"date": "2025-09-21T11:51:17.234000+00:00", "session_key": 9904, "driver_number": 1, "x": -14496, "meeting_key": 1269, "z": -217, "y": -10840}, {"date": "2025-09-21T11:51:17.514000+00:00", "session_key": 9904, "driver_number": 1, "x": -14346, "meeting_key": 1269, "z": -221, "y": -10928}, {"date": "2025-09-21T11:51:17.774000+00:00", "session_key": 9904, "driver_number": 1, "x": -14260, "meeting_key": 1269, "z": -224, "y": -10978}, {"date": "2025-09-21T11:51:17.914000+00:00", "session_key": 9904, "driver_number": 1, "x": -14150, "meeting_key": 1269, "z": -227, "y": -11036}, {"date": "2025-09-21T11:51:18.314000+00:00", "session_key": 9904, "driver_number": 1, "x": -14041, "meeting_key": 1269, "z": -230, "y": -11084}, {"date": "2025-09-21T11:51:18.633000+00:00", "session_key": 9904, "driver_number": 1, "x": -13928, "meeting_key": 1269, "z": -232, "y": -11120}, {"date": "2025-09-21T11:51:18.853000+00:00", "session_key": 9904, "driver_number": 1, "x": -13853, "meeting_key": 1269, "z": -234, "y": -11134}, {"date": "2025-09-21T11:51:19.053000+00:00", "session_key": 9904, "driver_number": 1, "x": -13789, "meeting_key": 1269, "z": -235, "y": -11137}, {"date": "2025-09-21T11:51:19.253000+00:00", "session_key": 9904, "driver_number": 1, "x": -13692, "meeting_key": 1269, "z": -236, "y": -11121}, {"date": "2025-09-21T11:51:19.573000+00:00", "session_key": 9904, "driver_number": 1, "x": -13638, "meeting_key": 1269, "z": -236, "y": -11097}, {"date": "2025-09-21T11:51:19.833000+00:00", "session_key": 9904, "driver_number": 1, "x": -13576, "meeting_key": 1269, "z": -237, "y": -11047}, {"date": "2025-09-21T11:51:19.933000+00:00", "session_key": 9904, "driver_number": 1, "x": -13554, "meeting_key": 1269, "z": -237, "y": -11023}, {"date": "2025-09-21T11:51:20.233000+00:00", "session_key": 9904, "driver_number": 1, "x": -13478, "meeting_key": 1269, "z": -238, "y": -10915}, {"date": "2025-09-21T11:51:20.613000+00:00", "session_key": 9904, "driver_number": 1, "x": -13431, "meeting_key": 1269, "z": -239, "y": -10829}, {"date": "2025-09-21T11:51:20.873000+00:00", "session_key": 9904, "driver_number": 1, "x": -13387, "meeting_key": 1269, "z": -239, "y": -10743}, {"date": "2025-09-21T11:51:20.973000+00:00", "session_key": 9904, "driver_number": 1, "x": -13370, "meeting_key": 1269, "z": -240, "y": -10709}, {"date": "2025-09-21T11:51:21.314000+00:00", "session_key": 9904, "driver_number": 1, "x": -13306, "meeting_key": 1269, "z": -241, "y": -10580}, {"date": "2025-09-21T11:51:21.494000+00:00", "session_key": 9904, "driver_number": 1, "x": -13244, "meeting_key": 1269, "z": -242, "y": -10455}, {"date": "2025-09-21T11:51:21.874000+00:00", "session_key": 9904, "driver_number": 1, "x": -13187, "meeting_key": 1269, "z": -242, "y": -10340}, {"date": "2025-09-21T11:51:22.034000+00:00", "session_key": 9904, "driver_number": 1, "x": -13150, "meeting_key": 1269, "z": -242, "y": -10265}, {"date": "2025-09-21T11:51:22.334000+00:00", "session_key": 9904, "driver_number": 1, "x": -13057, "meeting_key": 1269, "z": -242, "y": -10071}, {"date": "2025-09-21T11:51:22.654000+00:00", "session_key": 9904, "driver_number": 1, "x": -13001, "meeting_key": 1269, "z": -242, "y": -9958}, {"date": "2025-09-21T11:51:22.854000+00:00", "session_key": 9904, "driver_number": 1, "x": -12946, "meeting_key": 1269, "z": -242, "y": -9855}, {"date": "2025-09-21T11:51:23.094000+00:00", "session_key": 9904, "driver_number": 1, "x": -12874, "meeting_key": 1269, "z": -241, "y": -9729}, {"date": "2025-09-21T11:51:23.294000+00:00", "session_key": 9904, "driver_number": 1, "x": -12808, "meeting_key": 1269, "z": -241, "y": -9623}, {"date": "2025-09-21T11:51:23.554000+00:00", "session_key": 9904, "driver_number": 1, "x": -12672, "meeting_key": 1269, "z": -240, "y": -9422}, {"date": "2025-09-21T11:51:23.974000+00:00", "session_key": 9904, "driver_number": 1, "x": -12514, "meeting_key": 1269, "z": -240, "y": -9225}, {"date": "2025-09-21T11:51:24.414000+00:00", "session_key": 9904, "driver_number": 1, "x": -12268, "meeting_key": 1269, "z": -239, "y": -8981}, {"date": "2025-09-21T11:51:24.734000+00:00", "session_key": 9904, "driver_number": 1, "x": -12173, "meeting_key": 1269, "z": -239, "y": -8897}, {"date": "2025-09-21T11:51:25.014000+00:00", "session_key": 9904, "driver_number": 1, "x": -12019, "meeting_key": 1269, "z": -239, "y": -8765}, {"date": "2025-09-21T11:51:25.173000+00:00", "session_key": 9904, "driver_number": 1, "x": -11853, "meeting_key": 1269, "z": -239, "y": -8620}, {"date": "2025-09-21T11:51:25.593000+00:00", "session_key": 9904, "driver_number": 1, "x": -11637, "meeting_key": 1269, "z": -240, "y": -8413}, {"date": "2025-09-21T11:51:25.853000+00:00", "session_key": 9904, "driver_number": 1, "x": -11565, "meeting_key": 1269, "z": -240, "y": -8335}, {"date": "2025-09-21T11:51:26.073000+00:00", "session_key": 9904, "driver_number": 1, "x": -11451, "meeting_key": 1269, "z": -239, "y": -8211}, {"date": "2025-09-21T11:51:26.393000+00:00", "session_key": 9904, "driver_number": 1, "x": -11206, "meeting_key": 1269, "z": -239, "y": -7981}, {"date": "2025-09-21T11:51:26.633000+00:00", "session_key": 9904, "driver_number": 1, "x": -11075, "meeting_key": 1269, "z": -236, "y": -7848}, {"date": "2025-09-21T11:51:26.833000+00:00", "session_key": 9904, "driver_number": 1, "x": -10986, "meeting_key": 1269, "z": -237, "y": -7725}, {"date": "2025-09-21T11:51:26.933000+00:00", "session_key": 9904, "driver_number": 1, "x": -10947, "meeting_key": 1269, "z": -237, "y": -7657}, {"date": "2025-09-21T11:51:27.273000+00:00", "session_key": 9904, "driver_number": 1, "x": -10807, "meeting_key": 1269, "z": -237, "y": -7299}, {"date": "2025-09-21T11:51:27.513000+00:00", "session_key": 9904, "driver_number": 1, "x": -10785, "meeting_key": 1269, "z": -237, "y": -7222}, {"date": "2025-09-21T11:51:27.894000+00:00", "session_key": 9904, "driver_number": 1, "x": -10717, "meeting_key": 1269, "z": -237, "y": -6924}, {"date": "2025-09-21T11:51:27.934000+00:00", "session_key": 9904, "driver_number": 1, "x": -10710, "meeting_key": 1269, "z": -237, "y": -6892}, {"date": "2025-09-21T11:51:28.134000+00:00", "session_key": 9904, "driver_number": 1, "x": -10676, "meeting_key": 1269, "z": -238, "y": -6735}, {"date": "2025-09-21T11:51:28.354000+00:00", "session_key": 9904, "driver_number": 1, "x": -10629, "meeting_key": 1269, "z": -237, "y": -6566}, {"date": "2025-09-21T11:51:28.694000+00:00", "session_key": 9904, "driver_number": 1, "x": -10515, "meeting_key": 1269, "z": -237, "y": -6328}, {"date": "2025-09-21T11:51:28.874000+00:00", "session_key": 9904, "driver_number": 1, "x": -10425, "meeting_key": 1269, "z": -237, "y": -6213}, {"date": "2025-09-21T11:51:29.154000+00:00", "session_key": 9904, "driver_number": 1, "x": -10255, "meeting_key": 1269, "z": -236, "y": -6054}, {"date": "2025-09-21T11:51:29.334000+00:00", "session_key": 9904, "driver_number": 1, "x": -10136, "meeting_key": 1269, "z": -236, "y": -5962}, {"date": "2025-09-21T11:51:29.514000+00:00", "session_key": 9904, "driver_number": 1, "x": -10014, "meeting_key": 1269, "z": -236, "y": -5875}, {"date": "2025-09-21T11:51:29.754000+00:00", "session_key": 9904, "driver_number": 1, "x": -9853, "meeting_key": 1269, "z": -236, "y": -5760}, {"date": "2025-09-21T11:51:29.934000+00:00", "session_key": 9904, "driver_number": 1, "x": -9735, "meeting_key": 1269, "z": -235, "y": -5672}, {"date": "2025-09-21T11:51:30.074000+00:00", "session_key": 9904, "driver_number": 1, "x": -9643, "meeting_key": 1269, "z": -235, "y": -5601}, {"date": "2025-09-21T11:51:30.374000+00:00", "session_key": 9904, "driver_number": 1, "x": -9393, "meeting_key": 1269, "z": -236, "y": -5407}, {"date": "2025-09-21T11:51:30.654000+00:00", "session_key": 9904, "driver_number": 1, "x": -9260, "meeting_key": 1269, "z": -236, "y": -5306}, {"date": "2025-09-21T11:51:30.994000+00:00", "session_key": 9904, "driver_number": 1, "x": -9033, "meeting_key": 1269, "z": -237, "y": -5133}, {"date": "2025-09-21T11:51:31.114000+00:00", "session_key": 9904, "driver_number": 1, "x": -8952, "meeting_key": 1269, "z": -237, "y": -5071}, {"date": "2025-09-21T11:51:31.314000+00:00", "session_key": 9904, "driver_number": 1, "x": -8723, "meeting_key": 1269, "z": -237, "y": -4896}, {"date": "2025-09-21T11:51:31.753000+00:00", "session_key": 9904, "driver_number": 1, "x": -8519, "meeting_key": 1269, "z": -238, "y": -4742}, {"date": "2025-09-21T11:51:31.993000+00:00", "session_key": 9904, "driver_number": 1, "x": -8356, "meeting_key": 1269, "z": -238, "y": -4618}, {"date": "2025-09-21T11:51:32.193000+00:00", "session_key": 9904, "driver_number": 1, "x": -8154, "meeting_key": 1269, "z": -239, "y": -4459}, {"date": "2025-09-21T11:51:32.513000+00:00", "session_key": 9904, "driver_number": 1, "x": -8002, "meeting_key": 1269, "z": -239, "y": -4349}, {"date": "2025-09-21T11:51:32.733000+00:00", "session_key": 9904, "driver_number": 1, "x": -7843, "meeting_key": 1269, "z": -239, "y": -4249}, {"date": "2025-09-21T11:51:32.913000+00:00", "session_key": 9904, "driver_number": 1, "x": -7698, "meeting_key": 1269, "z": -239, "y": -4170}, {"date": "2025-09-21T11:51:33.233000+00:00", "session_key": 9904, "driver_number": 1, "x": -7339, "meeting_key": 1269, "z": -241, "y": -4010}, {"date": "2025-09-21T11:51:33.633000+00:00", "session_key": 9904, "driver_number": 1, "x": -7031, "meeting_key": 1269, "z": -241, "y": -3889}, {"date": "2025-09-21T11:51:34.013000+00:00", "session_key": 9904, "driver_number": 1, "x": -6804, "meeting_key": 1269, "z": -241, "y": -3799}, {"date": "2025-09-21T11:51:34.274000+00:00", "session_key": 9904, "driver_number": 1, "x": -6593, "meeting_key": 1269, "z": -242, "y": -3713}, {"date": "2025-09-21T11:51:34.434000+00:00", "session_key": 9904, "driver_number": 1, "x": -6463, "meeting_key": 1269, "z": -242, "y": -3661}, {"date": "2025-09-21T11:51:34.674000+00:00", "session_key": 9904, "driver_number": 1, "x": -6268, "meeting_key": 1269, "z": -242, "y": -3582}, {"date": "2025-09-21T11:51:34.854000+00:00", "session_key": 9904, "driver_number": 1, "x": -6122, "meeting_key": 1269, "z": -242, "y": -3522}, {"date": "2025-09-21T11:51:35.114000+00:00", "session_key": 9904, "driver_number": 1, "x": -5936, "meeting_key": 1269, "z": -242, "y": -3446}, {"date": "2025-09-21T11:51:35.294000+00:00", "session_key": 9904, "driver_number": 1, "x": -5805, "meeting_key": 1269, "z": -240, "y": -3391}, {"date": "2025-09-21T11:51:35.514000+00:00", "session_key": 9904, "driver_number": 1, "x": -5563, "meeting_key": 1269, "z": -239, "y": -3291}, {"date": "2025-09-21T11:51:35.914000+00:00", "session_key": 9904, "driver_number": 1, "x": -5303, "meeting_key": 1269, "z": -237, "y": -3182}, {"date": "2025-09-21T11:51:36.094000+00:00", "session_key": 9904, "driver_number": 1, "x": -5156, "meeting_key": 1269, "z": -237, "y": -3122}, {"date": "2025-09-21T11:51:36.334000+00:00", "session_key": 9904, "driver_number": 1, "x": -4895, "meeting_key": 1269, "z": -237, "y": -3013}, {"date": "2025-09-21T11:51:36.674000+00:00", "session_key": 9904, "driver_number": 1, "x": -4683, "meeting_key": 1269, "z": -238, "y": -2924}, {"date": "2025-09-21T11:51:36.894000+00:00", "session_key": 9904, "driver_number": 1, "x": -4504, "meeting_key": 1269, "z": -238, "y": -2847}, {"date": "2025-09-21T11:51:37.014000+00:00", "session_key": 9904, "driver_number": 1, "x": -4406, "meeting_key": 1269, "z": -238, "y": -2806}, {"date": "2025-09-21T11:51:37.234000+00:00", "session_key": 9904, "driver_number": 1, "x": -4226, "meeting_key": 1269, "z": -238, "y": -2730}, {"date": "2025-09-21T11:51:37.594000+00:00", "session_key": 9904, "driver_number": 1, "x": -3914, "meeting_key": 1269, "z": -236, "y": -2598}, {"date": "2025-09-21T11:51:37.934000+00:00", "session_key": 9904, "driver_number": 1, "x": -3651, "meeting_key": 1269, "z": -234, "y": -2487}, {"date": "2025-09-21T11:51:38.134000+00:00", "session_key": 9904, "driver_number": 1, "x": -3388, "meeting_key": 1269, "z": -233, "y": -2376}, {"date": "2025-09-21T11:51:38.453000+00:00", "session_key": 9904, "driver_number": 1, "x": -3223, "meeting_key": 1269, "z": -232, "y": -2306}, {"date": "2025-09-21T11:51:38.753000+00:00", "session_key": 9904, "driver_number": 1, "x": -2976, "meeting_key": 1269, "z": -233, "y": -2201}, {"date": "2025-09-21T11:51:38.933000+00:00", "session_key": 9904, "driver_number": 1, "x": -2828, "meeting_key": 1269, "z": -233, "y": -2139}, {"date": "2025-09-21T11:51:39.053000+00:00", "session_key": 9904, "driver_number": 1, "x": -2729, "meeting_key": 1269, "z": -234, "y": -2097}, {"date": "2025-09-21T11:51:39.393000+00:00", "session_key": 9904, "driver_number": 1, "x": -2333, "meeting_key": 1269, "z": -235, "y": -1928}, {"date": "2025-09-21T11:51:39.773000+00:00", "session_key": 9904, "driver_number": 1, "x": -2013, "meeting_key": 1269, "z": -237, "y": -1796}, {"date": "2025-09-21T11:51:40.173000+00:00", "session_key": 9904, "driver_number": 1, "x": -1678, "meeting_key": 1269, "z": -238, "y": -1665}, {"date": "2025-09-21T11:51:40.533000+00:00", "session_key": 9904, "driver_number": 1, "x": -1493, "meeting_key": 1269, "z": -239, "y": -1597}, {"date": "2025-09-21T11:51:40.854000+00:00", "session_key": 9904, "driver_number": 1, "x": -1104, "meeting_key": 1269, "z": -241, "y": -1452}, {"date": "2025-09-21T11:51:41.094000+00:00", "session_key": 9904, "driver_number": 1, "x": -1020, "meeting_key": 1269, "z": -241, "y": -1421}, {"date": "2025-09-21T11:51:41.354000+00:00", "session_key": 9904, "driver_number": 1, "x": -801, "meeting_key": 1269, "z": -242, "y": -1338}, {"date": "2025-09-21T11:51:41.554000+00:00", "session_key": 9904, "driver_number": 1, "x": -633, "meeting_key": 1269, "z": -243, "y": -1275}, {"date": "2025-09-21T11:51:41.754000+00:00", "session_key": 9904, "driver_number": 1, "x": -465, "meeting_key": 1269, "z": -243, "y": -1213}, {"date": "2025-09-21T11:51:41.974000+00:00", "session_key": 9904, "driver_number": 1, "x": -279, "meeting_key": 1269, "z": -244, "y": -1144}, {"date": "2025-09-21T11:51:42.294000+00:00", "session_key": 9904, "driver_number": 1, "x": 89, "meeting_key": 1269, "z": -245, "y": -1002}, {"date": "2025-09-21T11:51:42.714000+00:00", "session_key": 9904, "driver_number": 1, "x": 389, "meeting_key": 1269, "z": -247, "y": -876}, {"date": "2025-09-21T11:51:42.994000+00:00", "session_key": 9904, "driver_number": 1, "x": 573, "meeting_key": 1269, "z": -246, "y": -797}, {"date": "2025-09-21T11:51:43.274000+00:00", "session_key": 9904, "driver_number": 1, "x": 804, "meeting_key": 1269, "z": -246, "y": -699}, {"date": "2025-09-21T11:51:43.514000+00:00", "session_key": 9904, "driver_number": 1, "x": 998, "meeting_key": 1269, "z": -246, "y": -619}, {"date": "2025-09-21T11:51:43.754000+00:00", "session_key": 9904, "driver_number": 1, "x": 1228, "meeting_key": 1269, "z": -245, "y": -524}, {"date": "2025-09-21T11:51:44.194000+00:00", "session_key": 9904, "driver_number": 1, "x": 1555, "meeting_key": 1269, "z": -244, "y": -388}, {"date": "2025-09-21T11:51:44.254000+00:00", "session_key": 9904, "driver_number": 1, "x": 1604, "meeting_key": 1269, "z": -244, "y": -367}, {"date": "2025-09-21T11:51:44.574000+00:00", "session_key": 9904, "driver_number": 1, "x": 1978, "meeting_key": 1269, "z": -243, "y": -210}, {"date": "2025-09-21T11:51:44.854000+00:00", "session_key": 9904, "driver_number": 1, "x": 2091, "meeting_key": 1269, "z": -243, "y": -162}, {"date": "2025-09-21T11:51:45.113000+00:00", "session_key": 9904, "driver_number": 1, "x": 2301, "meeting_key": 1269, "z": -243, "y": -75}]